{"cameraMode":{"drawMode":0,"name":"Shaded","section":"Shading Mode"},"sceneLighting":true,"audioPlay":false,"sceneViewState":{"showFog":true,"showMaterialUpdate":false,"showSkybox":true,"showFlares":true,"showImageEffects":true,"showParticleSystems":true},"in2DMode":false,"pivot":{"x":5.700770378112793,"y":1.4905529022216797,"z":1.8753187656402588},"rotation":{"x":0.23763029277324677,"y":0.5488840937614441,"z":-0.16637594997882844,"w":0.7839765548706055},"size":6.068655967712402,"orthographic":false}